pyrestream/__init__.py
pyrestream/api.py
pyrestream/auth.py
pyrestream/config.py
pyrestream/errors.py
pyrestream/utils.py
pyrestream/websocket.py
pyrestream/schemas/Channel.py
pyrestream/schemas/ChannelMeta.py
pyrestream/schemas/ChannelSummary.py
pyrestream/schemas/ChatEvent.py
pyrestream/schemas/EventDestination.py
pyrestream/schemas/EventsHistoryResponse.py
pyrestream/schemas/EventsPagination.py
pyrestream/schemas/Platform.py
pyrestream/schemas/PlatformImage.py
pyrestream/schemas/Profile.py
pyrestream/schemas/Server.py
pyrestream/schemas/StreamEvent.py
pyrestream/schemas/StreamKey.py
pyrestream/schemas/StreamingEvent.py
pyrestream/schemas/__init__.py
pyrestream-0.6.0.dist-info/METADATA
pyrestream-0.6.0.dist-info/WHEEL
pyrestream-0.6.0.dist-info/top_level.txt
pyrestream-0.6.0.dist-info/RECORD
