Metadata-Version: 2.4
Name: pyrestream
Version: 0.6.0
Summary: Python client library for the Restream.io REST API and WebSocket APIs
License: BSD-3-Clause
Requires-Python: >=3.11
Requires-Dist: attrs>=25.3.0
Requires-Dist: requests>=2.32.4
Requires-Dist: websockets>=14.1
